.gitignore
.gitmodules
HISTORY.rst
LICENCE
MANIFEST.in
Makefile
README.rst
distribute_setup.py
setup.py
/Users/dinoboff/Documents/workspace/skeleton/src/build/lib/skeleton.egg-info/SOURCES.txt
docs/Makefile
docs/api.rst
docs/conf.py
docs/history.rst
docs/index.rst
docs/make.bat
docs/overview.rst
skeleton/__init__.py
skeleton/core.py
skeleton/utils.py
skeleton/examples/__init__.py
skeleton/examples/basicpackage.py
skeleton/examples/licenses.py
skeleton/examples/mkmodule.py
skeleton/examples/basic-module/README.rst
skeleton/examples/basic-module/setup.py_tmpl
skeleton/examples/basic-module/{module_name}.py
skeleton/examples/basic-package/MANIFEST.in
skeleton/examples/basic-package/README.rst
skeleton/examples/basic-package/distribute_setup.py
skeleton/examples/basic-package/setup.py_tmpl
skeleton/examples/licenses/bsd/LICENSE_tmpl
skeleton/examples/licenses/gpl/COPYING
skeleton/examples/licenses/gpl/LICENSE_tmpl
skeleton/examples/licenses/lgpl/COPYING
skeleton/examples/licenses/lgpl/COPYING.LESSER
skeleton/examples/licenses/lgpl/LICENSE_tmpl
skeleton/examples/licenses/no-license/LICENSE_tmpl
skeleton/tests/__init__.py
skeleton/tests/test_core.py
skeleton/tests/test_examples.py
skeleton/tests/test_utils.py
skeleton/tests/utils.py
skeleton/tests/skeletons/dynamic-content/foo.txt
skeleton/tests/skeletons/dynamic-content/bar/baz.txt_tmpl
skeleton/tests/skeletons/dynamic-file-name/foo.txt
skeleton/tests/skeletons/dynamic-file-name/bar/{baz}.txt
skeleton/tests/skeletons/required/{file_name}.txt
skeleton/tests/skeletons/required/bar/empty
skeleton/tests/skeletons/static/foo.txt
skeleton/tests/skeletons/static/bar/baz.txt