Metadata-Version: 1.0
Name: skeleton
Version: 0.6
Summary: Basic Template system for project skeleton.
Home-page: http://github.com/dinoboff/skeleton
Author: Damien Lebrun
Author-email: dinoboff@gmail.com
License: BSD
Platform: UNKNOWN
Classifier: Development Status :: 4 - Beta
Classifier: Environment :: Console
Classifier: License :: OSI Approved :: BSD License
Classifier: Operating System :: OS Independent
Classifier: Programming Language :: Python
Classifier: Programming Language :: Python :: 2.6
Classifier: Programming Language :: Python :: 3
Classifier: Programming Language :: Python :: 3.1
